subscope
