Metadata-Version: 1.1
Name: subscope
Version: 1.0.1
Summary: A command line tool to download subtitles for your movies.
Home-page: UNKNOWN
Author: Julien Pagès
Author-email: j.parkouss@gmail.com
License: GPLv3
Keywords: subtitles movies srt download opensubtitles thesubdb
Platform: UNKNOWN
Classifier: Development Status :: 3 - Alpha
Classifier: Topic :: Utilities
Classifier: License :: OSI Approved :: GNU General Public License v3 (GPLv3)
Classifier: Environment :: Console
Classifier: Operating System :: OS Independent
Classifier: Programming Language :: Python :: 2
Classifier: Programming Language :: Python :: 2.7
Classifier: Programming Language :: Python :: 3
Classifier: Programming Language :: Python :: 3.3
Classifier: Programming Language :: Python :: 3.4
